[{"auditorium":"5-201","auditoriumAmount":30,"auditoriumOid":335,"author":"lena","beginLesson":"11:35","building":"УЛК-5","buildingGid":13,"buildingOid":13,"contentOfLoadOid":2589,"contentOfLoadUID":null,"contentTableOfLessonsName":"3","contentTableOfLessonsOid":3,"createddate":"2022-09-06T12:36:38Z00:00","date":"2022.09.13","dateOfNest":"\/Date(1663005600000+0600)\/","dayOfWeek":2,"dayOfWeekString":"Tue","detailInfo":"","discipline":"Безопасность жизнедеятельности","disciplineOid":5577,"disciplineinplan":null,"disciplinetypeload":0,"duration":2,"endLesson":"13:05","group":null,"groupOid":0,"groupUID":null,"group_facultyoid":0,"hideincapacity":0,"isBan":false,"kindOfWork":"Лекция","kindOfWorkComplexity":0,"kindOfWorkOid":2,"kindOfWorkUid":null,"lecturer":"доц., к.н. ЯНЧИЙ С.В.","lecturerCustomUID":null,"lecturerEmail":"","lecturerOid":252,"lecturerUID":null,"lecturer_rank":"доц., к.н.","lecturer_title":"ЯНЧИЙ С.В.","lessonNumberEnd":3,"lessonNumberStart":3,"lessonOid":140779,"listOfLecturers":[{"lecturer":"доц., к.н. ЯНЧИЙ С.В.","lecturerCustomUID":null,"lecturerEmail":"","lecturerOid":252,"lecturerUID":null,"lecturer_rank":"доц., к.н.","lecturer_title":"ЯНЧИЙ С.В."}],"modifieddate":"2022-09-06T12:36:38Z00:00","note":null,"note_description":"","parentschedule":"ЗМСИ-19   2 нач. 1 сем.      ПОЛУКОВА Е.А.","replaces":null,"stream":"Поток(ЗС-191)","streamOid":315,"stream_facultyoid":18,"subGroup":null,"subGroupOid":0,"subgroup_facultyoid":0,"tableofLessonsName":"Общий распорядок пар","tableofLessonsOid":1,"url1":"","url1_description":"","url2":"","url2_description":""},{"auditorium":"6-107б","auditoriumAmount":24,"auditoriumOid":312,"author":"lena","beginLesson":"13:15","building":"УЛК-6","buildingGid":14,"buildingOid":14,"contentOfLoadOid":30,"contentOfLoadUID":null,"contentTableOfLessonsName":"4","contentTableOfLessonsOid":4,"createddate":"2022-09-12T09:44:43Z00:00","date":"2022.09.13","dateOfNest":"\/Date(1663005600000+0600)\/","dayOfWeek":2,"dayOfWeekString":"Tue","detailInfo":"","discipline":"Источники питания для сварки","disciplineOid":826,"disciplineinplan":null,"disciplinetypeload":0,"duration":2,"endLesson":"14:45","group":null,"groupOid":0,"groupUID":null,"group_facultyoid":0,"hideincapacity":0,"isBan":false,"kindOfWork":"Лекция","kindOfWorkComplexity":0,"kindOfWorkOid":2,"kindOfWorkUid":null,"lecturer":"проф., д.н. ЕРЕМИН Е.Н.","lecturerCustomUID":null,"lecturerEmail":"","lecturerOid":145,"lecturerUID":null,"lecturer_rank":"проф., д.н.","lecturer_title":"ЕРЕМИН Е.Н.","lessonNumberEnd":4,"lessonNumberStart":4,"lessonOid":145336,"listOfLecturers":[{"lecturer":"проф., д.н. ЕРЕМИН Е.Н.","lecturerCustomUID":null,"lecturerEmail":"","lecturerOid":145,"lecturerUID":null,"lecturer_rank":"проф., д.н.","lecturer_title":"ЕРЕМИН Е.Н."}],"modifieddate":"2022-09-12T09:44:43Z00:00","note":null,"note_description":"","parentschedule":"ЗМСИ-19   2 нач. 1 сем.      ПОЛУКОВА Е.А.","replaces":null,"stream":"Поток(ЗМ-191, ЗС-191)","streamOid":267,"stream_facultyoid":18,"subGroup":null,"subGroupOid":0,"subgroup_facultyoid":0,"tableofLessonsName":"Общий распорядок пар","tableofLessonsOid":1,"url1":"","url1_description":"","url2":"","url2_description":""},{"auditorium":"6-429","auditoriumAmount":99,"auditoriumOid":227,"author":"lena","beginLesson":"15:10","building":"УЛК-6","buildingGid":14,"buildingOid":14,"contentOfLoadOid":65,"contentOfLoadUID":null,"contentTableOfLessonsName":"5","contentTableOfLessonsOid":5,"createddate":"2022-09-06T12:20:57Z00:00","date":"2022.09.13","dateOfNest":"\/Date(1663005600000+0600)\/","dayOfWeek":2,"dayOfWeekString":"Tue","detailInfo":"","discipline":"Теория сварочных процессов","disciplineOid":844,"disciplineinplan":null,"disciplinetypeload":0,"duration":2,"endLesson":"16:40","group":null,"groupOid":0,"groupUID":null,"group_facultyoid":0,"hideincapacity":0,"isBan":false,"kindOfWork":"Лекция","kindOfWorkComplexity":0,"kindOfWorkOid":2,"kindOfWorkUid":null,"lecturer":"ст.пр. ЛОСЕВ А.С.","lecturerCustomUID":null,"lecturerEmail":"","lecturerOid":21,"lecturerUID":null,"lecturer_rank":"ст.пр.","lecturer_title":"ЛОСЕВ А.С.","lessonNumberEnd":5,"lessonNumberStart":5,"lessonOid":140697,"listOfLecturers":[{"lecturer":"ст.пр. ЛОСЕВ А.С.","lecturerCustomUID":null,"lecturerEmail":"","lecturerOid":21,"lecturerUID":null,"lecturer_rank":"ст.пр.","lecturer_title":"ЛОСЕВ А.С."}],"modifieddate":"2022-09-06T12:20:57Z00:00","note":null,"note_description":"","parentschedule":"ЗМСИ-19   2 нач. 1 сем.      ПОЛУКОВА Е.А.","replaces":null,"stream":"Поток(ЗС-191)","streamOid":315,"stream_facultyoid":18,"subGroup":null,"subGroupOid":0,"subgroup_facultyoid":0,"tableofLessonsName":"Общий распорядок пар","tableofLessonsOid":1,"url1":"","url1_description":"","url2":"","url2_description":""},{"auditorium":"6-220","auditoriumAmount":36,"auditoriumOid":280,"author":"lena","beginLesson":"16:50","building":"УЛК-6","buildingGid":14,"buildingOid":14,"contentOfLoadOid":40,"contentOfLoadUID":null,"contentTableOfLessonsName":"6","contentTableOfLessonsOid":6,"createddate":"2022-09-06T12:21:08Z00:00","date":"2022.09.13","dateOfNest":"\/Date(1663005600000+0600)\/","dayOfWeek":2,"dayOfWeekString":"Tue","detailInfo":"","discipline":"Контроль качества сварных конструкций","disciplineOid":829,"disciplineinplan":null,"disciplinetypeload":0,"duration":2,"endLesson":"18:20","group":null,"groupOid":0,"groupUID":null,"group_facultyoid":0,"hideincapacity":0,"isBan":false,"kindOfWork":"Лекция","kindOfWorkComplexity":0,"kindOfWorkOid":2,"kindOfWorkUid":null,"lecturer":"доц., к.н. СОКОЛОВ В.А.","lecturerCustomUID":null,"lecturerEmail":"","lecturerOid":292,"lecturerUID":null,"lecturer_rank":"доц., к.н.","lecturer_title":"СОКОЛОВ В.А.","lessonNumberEnd":6,"lessonNumberStart":6,"lessonOid":140698,"listOfLecturers":[{"lecturer":"доц., к.н. СОКОЛОВ В.А.","lecturerCustomUID":null,"lecturerEmail":"","lecturerOid":292,"lecturerUID":null,"lecturer_rank":"доц., к.н.","lecturer_title":"СОКОЛОВ В.А."}],"modifieddate":"2022-09-06T12:21:08Z00:00","note":null,"note_description":"","parentschedule":"ЗМСИ-19   2 нач. 1 сем.      ПОЛУКОВА Е.А.","replaces":null,"stream":"Поток(ЗС-191)","streamOid":315,"stream_facultyoid":18,"subGroup":null,"subGroupOid":0,"subgroup_facultyoid":0,"tableofLessonsName":"Общий распорядок пар","tableofLessonsOid":1,"url1":"","url1_description":"","url2":"","url2_description":""}]