[{"auditorium":"8-801","auditoriumAmount":25,"auditoriumOid":93,"author":"kristina","beginLesson":"15:10","building":"УЛК-8","buildingGid":16,"buildingOid":16,"contentOfLoadOid":8565,"contentOfLoadUID":null,"contentTableOfLessonsName":"5","contentTableOfLessonsOid":5,"createddate":"2022-08-02T11:59:20Z00:00","date":"2022.09.13","dateOfNest":"\/Date(1663005600000+0600)\/","dayOfWeek":2,"dayOfWeekString":"Tue","detailInfo":"","discipline":"Учебная практика (научно-исследовательская работа (получение первичных навыков научно-исследовательской работы)","disciplineOid":6056,"disciplineinplan":null,"disciplinetypeload":0,"duration":2,"endLesson":"16:40","group":"КРм-211","groupOid":463,"groupUID":null,"group_facultyoid":10,"hideincapacity":0,"isBan":false,"kindOfWork":"Практические занятия","kindOfWorkComplexity":0,"kindOfWorkOid":4,"kindOfWorkUid":null,"lecturer":"доц., к.н. ДОЛГАНЕВ Ю.Г.","lecturerCustomUID":null,"lecturerEmail":"","lecturerOid":427,"lecturerUID":null,"lecturer_rank":"доц., к.н.","lecturer_title":"ДОЛГАНЕВ Ю.Г.","lessonNumberEnd":5,"lessonNumberStart":5,"lessonOid":98824,"listOfLecturers":[{"lecturer":"доц., к.н. ДОЛГАНЕВ Ю.Г.","lecturerCustomUID":null,"lecturerEmail":"","lecturerOid":427,"lecturerUID":null,"lecturer_rank":"доц., к.н.","lecturer_title":"ДОЛГАНЕВ Ю.Г."}],"modifieddate":"2022-08-02T11:59:20Z00:00","note":null,"note_description":"","parentschedule":"МАГИСТРЫ-21 + НДм, СМм, 1 СЕМЕСТР, ПОСТнИКОВА","replaces":null,"stream":null,"streamOid":0,"stream_facultyoid":0,"subGroup":null,"subGroupOid":0,"subgroup_facultyoid":0,"tableofLessonsName":"Общий распорядок пар","tableofLessonsOid":1,"url1":"","url1_description":"","url2":"","url2_description":""},{"auditorium":"8-801","auditoriumAmount":25,"auditoriumOid":93,"author":"kristina","beginLesson":"16:50","building":"УЛК-8","buildingGid":16,"buildingOid":16,"contentOfLoadOid":8565,"contentOfLoadUID":null,"contentTableOfLessonsName":"6","contentTableOfLessonsOid":6,"createddate":"2022-08-02T11:59:26Z00:00","date":"2022.09.13","dateOfNest":"\/Date(1663005600000+0600)\/","dayOfWeek":2,"dayOfWeekString":"Tue","detailInfo":"","discipline":"Учебная практика (научно-исследовательская работа (получение первичных навыков научно-исследовательской работы)","disciplineOid":6056,"disciplineinplan":null,"disciplinetypeload":0,"duration":2,"endLesson":"18:20","group":"КРм-211","groupOid":463,"groupUID":null,"group_facultyoid":10,"hideincapacity":0,"isBan":false,"kindOfWork":"Практические занятия","kindOfWorkComplexity":0,"kindOfWorkOid":4,"kindOfWorkUid":null,"lecturer":"доц., к.н. ДОЛГАНЕВ Ю.Г.","lecturerCustomUID":null,"lecturerEmail":"","lecturerOid":427,"lecturerUID":null,"lecturer_rank":"доц., к.н.","lecturer_title":"ДОЛГАНЕВ Ю.Г.","lessonNumberEnd":6,"lessonNumberStart":6,"lessonOid":98825,"listOfLecturers":[{"lecturer":"доц., к.н. ДОЛГАНЕВ Ю.Г.","lecturerCustomUID":null,"lecturerEmail":"","lecturerOid":427,"lecturerUID":null,"lecturer_rank":"доц., к.н.","lecturer_title":"ДОЛГАНЕВ Ю.Г."}],"modifieddate":"2022-08-02T11:59:26Z00:00","note":null,"note_description":"","parentschedule":"МАГИСТРЫ-21 + НДм, СМм, 1 СЕМЕСТР, ПОСТнИКОВА","replaces":null,"stream":null,"streamOid":0,"stream_facultyoid":0,"subGroup":null,"subGroupOid":0,"subgroup_facultyoid":0,"tableofLessonsName":"Общий распорядок пар","tableofLessonsOid":1,"url1":"","url1_description":"","url2":"","url2_description":""},{"auditorium":"8-101","auditoriumAmount":24,"auditoriumOid":189,"author":"kristina","beginLesson":"18:30","building":"УЛК-8","buildingGid":16,"buildingOid":16,"contentOfLoadOid":7615,"contentOfLoadUID":null,"contentTableOfLessonsName":"7","contentTableOfLessonsOid":7,"createddate":"2022-08-22T15:20:32Z00:00","date":"2022.09.13","dateOfNest":"\/Date(1663005600000+0600)\/","dayOfWeek":2,"dayOfWeekString":"Tue","detailInfo":"","discipline":"Обеспечение информационной безопасности в инфокоммуникациях","disciplineOid":5824,"disciplineinplan":null,"disciplinetypeload":0,"duration":2,"endLesson":"20:00","group":"КРм-211","groupOid":463,"groupUID":null,"group_facultyoid":10,"hideincapacity":0,"isBan":false,"kindOfWork":"Практические занятия","kindOfWorkComplexity":0,"kindOfWorkOid":4,"kindOfWorkUid":null,"lecturer":"доц., к.н. Щерба М.В.","lecturerCustomUID":null,"lecturerEmail":"","lecturerOid":980,"lecturerUID":null,"lecturer_rank":"доц., к.н.","lecturer_title":"Щерба М.В.","lessonNumberEnd":7,"lessonNumberStart":7,"lessonOid":110432,"listOfLecturers":[{"lecturer":"доц., к.н. Щерба М.В.","lecturerCustomUID":null,"lecturerEmail":"","lecturerOid":980,"lecturerUID":null,"lecturer_rank":"доц., к.н.","lecturer_title":"Щерба М.В."}],"modifieddate":"2022-08-22T15:20:32Z00:00","note":null,"note_description":"","parentschedule":"МАГИСТРЫ-21 + НДм, СМм, 1 СЕМЕСТР, ПОСТнИКОВА","replaces":null,"stream":null,"streamOid":0,"stream_facultyoid":0,"subGroup":null,"subGroupOid":0,"subgroup_facultyoid":0,"tableofLessonsName":"Общий распорядок пар","tableofLessonsOid":1,"url1":"","url1_description":"","url2":"","url2_description":""},{"auditorium":"8-101","auditoriumAmount":24,"auditoriumOid":189,"author":"kristina","beginLesson":"20:10","building":"УЛК-8","buildingGid":16,"buildingOid":16,"contentOfLoadOid":7615,"contentOfLoadUID":null,"contentTableOfLessonsName":"8","contentTableOfLessonsOid":8,"createddate":"2022-08-22T15:20:41Z00:00","date":"2022.09.13","dateOfNest":"\/Date(1663005600000+0600)\/","dayOfWeek":2,"dayOfWeekString":"Tue","detailInfo":"","discipline":"Обеспечение информационной безопасности в инфокоммуникациях","disciplineOid":5824,"disciplineinplan":null,"disciplinetypeload":0,"duration":2,"endLesson":"21:40","group":"КРм-211","groupOid":463,"groupUID":null,"group_facultyoid":10,"hideincapacity":0,"isBan":false,"kindOfWork":"Практические занятия","kindOfWorkComplexity":0,"kindOfWorkOid":4,"kindOfWorkUid":null,"lecturer":"доц., к.н. Щерба М.В.","lecturerCustomUID":null,"lecturerEmail":"","lecturerOid":980,"lecturerUID":null,"lecturer_rank":"доц., к.н.","lecturer_title":"Щерба М.В.","lessonNumberEnd":8,"lessonNumberStart":8,"lessonOid":110433,"listOfLecturers":[{"lecturer":"доц., к.н. Щерба М.В.","lecturerCustomUID":null,"lecturerEmail":"","lecturerOid":980,"lecturerUID":null,"lecturer_rank":"доц., к.н.","lecturer_title":"Щерба М.В."}],"modifieddate":"2022-08-22T15:20:41Z00:00","note":null,"note_description":"","parentschedule":"МАГИСТРЫ-21 + НДм, СМм, 1 СЕМЕСТР, ПОСТнИКОВА","replaces":null,"stream":null,"streamOid":0,"stream_facultyoid":0,"subGroup":null,"subGroupOid":0,"subgroup_facultyoid":0,"tableofLessonsName":"Общий распорядок пар","tableofLessonsOid":1,"url1":"","url1_description":"","url2":"","url2_description":""}]