[{"auditorium":"5-404","auditoriumAmount":56,"auditoriumOid":326,"author":"kristina","beginLesson":"16:50","building":"УЛК-5","buildingGid":13,"buildingOid":13,"contentOfLoadOid":7225,"contentOfLoadUID":null,"contentTableOfLessonsName":"6","contentTableOfLessonsOid":6,"createddate":"2022-09-11T21:44:24Z00:00","date":"2022.09.21","dateOfNest":"\/Date(1663696800000+0600)\/","dayOfWeek":3,"dayOfWeekString":"Wed","detailInfo":"","discipline":"Стратегическое региональное управление","disciplineOid":7377,"disciplineinplan":null,"disciplinetypeload":0,"duration":2,"endLesson":"18:20","group":null,"groupOid":0,"groupUID":null,"group_facultyoid":0,"hideincapacity":0,"isBan":false,"kindOfWork":"Лекция","kindOfWorkComplexity":0,"kindOfWorkOid":2,"kindOfWorkUid":null,"lecturer":"проф., к.н. СПИРИДОНОВА Т.В.","lecturerCustomUID":null,"lecturerEmail":"","lecturerOid":135,"lecturerUID":null,"lecturer_rank":"проф., к.н.","lecturer_title":"СПИРИДОНОВА Т.В.","lessonNumberEnd":6,"lessonNumberStart":6,"lessonOid":145056,"listOfLecturers":[{"lecturer":"проф., к.н. СПИРИДОНОВА Т.В.","lecturerCustomUID":null,"lecturerEmail":"","lecturerOid":135,"lecturerUID":null,"lecturer_rank":"проф., к.н.","lecturer_title":"СПИРИДОНОВА Т.В."}],"modifieddate":"2022-09-11T21:44:24Z00:00","note":null,"note_description":"","parentschedule":"МАГИСТРЫ-22 РТФ+ НДм, СМм, 1 СЕМЕСТР, ПОСТНИКОВА","replaces":null,"stream":"Поток(ГМУм-221)","streamOid":161,"stream_facultyoid":10,"subGroup":null,"subGroupOid":0,"subgroup_facultyoid":0,"tableofLessonsName":"Общий распорядок пар","tableofLessonsOid":1,"url1":"","url1_description":"","url2":"","url2_description":""},{"auditorium":"5-404","auditoriumAmount":56,"auditoriumOid":326,"author":"kristina","beginLesson":"18:30","building":"УЛК-5","buildingGid":13,"buildingOid":13,"contentOfLoadOid":7223,"contentOfLoadUID":null,"contentTableOfLessonsName":"7","contentTableOfLessonsOid":7,"createddate":"2022-09-11T21:44:35Z00:00","date":"2022.09.21","dateOfNest":"\/Date(1663696800000+0600)\/","dayOfWeek":3,"dayOfWeekString":"Wed","detailInfo":"","discipline":"Экономическое развитие регионов России","disciplineOid":7375,"disciplineinplan":null,"disciplinetypeload":0,"duration":2,"endLesson":"20:00","group":null,"groupOid":0,"groupUID":null,"group_facultyoid":0,"hideincapacity":0,"isBan":false,"kindOfWork":"Лекция","kindOfWorkComplexity":0,"kindOfWorkOid":2,"kindOfWorkUid":null,"lecturer":"проф., к.н. СПИРИДОНОВА Т.В.","lecturerCustomUID":null,"lecturerEmail":"","lecturerOid":135,"lecturerUID":null,"lecturer_rank":"проф., к.н.","lecturer_title":"СПИРИДОНОВА Т.В.","lessonNumberEnd":7,"lessonNumberStart":7,"lessonOid":145057,"listOfLecturers":[{"lecturer":"проф., к.н. СПИРИДОНОВА Т.В.","lecturerCustomUID":null,"lecturerEmail":"","lecturerOid":135,"lecturerUID":null,"lecturer_rank":"проф., к.н.","lecturer_title":"СПИРИДОНОВА Т.В."}],"modifieddate":"2022-09-11T21:44:35Z00:00","note":null,"note_description":"","parentschedule":"МАГИСТРЫ-22 РТФ+ НДм, СМм, 1 СЕМЕСТР, ПОСТНИКОВА","replaces":null,"stream":"Поток(ГМУм-221)","streamOid":161,"stream_facultyoid":10,"subGroup":null,"subGroupOid":0,"subgroup_facultyoid":0,"tableofLessonsName":"Общий распорядок пар","tableofLessonsOid":1,"url1":"","url1_description":"","url2":"","url2_description":""}]