[{"auditorium":"6-217","auditoriumAmount":16,"auditoriumOid":281,"author":"sveta","beginLesson":"11:35","building":"УЛК-6","buildingGid":14,"buildingOid":14,"contentOfLoadOid":9707,"contentOfLoadUID":null,"contentTableOfLessonsName":"3","contentTableOfLessonsOid":3,"createddate":"2022-06-24T12:07:27Z00:00","date":"2022.09.20","dateOfNest":"\/Date(1663610400000+0600)\/","dayOfWeek":2,"dayOfWeekString":"Tue","detailInfo":"","discipline":"Основы криогенной техники","disciplineOid":6957,"disciplineinplan":null,"disciplinetypeload":0,"duration":2,"endLesson":"13:05","group":"Х-201","groupOid":746,"groupUID":null,"group_facultyoid":12,"hideincapacity":0,"isBan":false,"kindOfWork":"Практические занятия","kindOfWorkComplexity":0,"kindOfWorkOid":4,"kindOfWorkUid":null,"lecturer":"проф., д.н. КАРАГУСОВ В.И.","lecturerCustomUID":null,"lecturerEmail":"","lecturerOid":157,"lecturerUID":null,"lecturer_rank":"проф., д.н.","lecturer_title":"КАРАГУСОВ В.И.","lessonNumberEnd":3,"lessonNumberStart":3,"lessonOid":66393,"listOfLecturers":[{"lecturer":"проф., д.н. КАРАГУСОВ В.И.","lecturerCustomUID":null,"lecturerEmail":"","lecturerOid":157,"lecturerUID":null,"lecturer_rank":"проф., д.н.","lecturer_title":"КАРАГУСОВ В.И."}],"modifieddate":"2022-06-24T12:07:27Z00:00","note":null,"note_description":"","parentschedule":"1 СЕМ.  НХИ-20  + БИО-201    СВЕТА","replaces":null,"stream":null,"streamOid":0,"stream_facultyoid":0,"subGroup":null,"subGroupOid":0,"subgroup_facultyoid":0,"tableofLessonsName":"Общий распорядок пар","tableofLessonsOid":1,"url1":"","url1_description":"","url2":"","url2_description":""},{"auditorium":"6-436","auditoriumAmount":58,"auditoriumOid":222,"author":"sveta","beginLesson":"13:15","building":"УЛК-6","buildingGid":14,"buildingOid":14,"contentOfLoadOid":9706,"contentOfLoadUID":null,"contentTableOfLessonsName":"4","contentTableOfLessonsOid":4,"createddate":"2022-06-24T11:55:36Z00:00","date":"2022.09.20","dateOfNest":"\/Date(1663610400000+0600)\/","dayOfWeek":2,"dayOfWeekString":"Tue","detailInfo":"","discipline":"Основы криогенной техники","disciplineOid":6957,"disciplineinplan":null,"disciplinetypeload":0,"duration":2,"endLesson":"14:45","group":null,"groupOid":0,"groupUID":null,"group_facultyoid":0,"hideincapacity":0,"isBan":false,"kindOfWork":"Лекция","kindOfWorkComplexity":0,"kindOfWorkOid":2,"kindOfWorkUid":null,"lecturer":"проф., д.н. КАРАГУСОВ В.И.","lecturerCustomUID":null,"lecturerEmail":"","lecturerOid":157,"lecturerUID":null,"lecturer_rank":"проф., д.н.","lecturer_title":"КАРАГУСОВ В.И.","lessonNumberEnd":4,"lessonNumberStart":4,"lessonOid":66327,"listOfLecturers":[{"lecturer":"проф., д.н. КАРАГУСОВ В.И.","lecturerCustomUID":null,"lecturerEmail":"","lecturerOid":157,"lecturerUID":null,"lecturer_rank":"проф., д.н.","lecturer_title":"КАРАГУСОВ В.И."}],"modifieddate":"2022-06-24T11:55:46Z00:00","note":null,"note_description":"","parentschedule":"1 СЕМ.  НХИ-20  + БИО-201    СВЕТА","replaces":null,"stream":"Поток(Х-201)","streamOid":865,"stream_facultyoid":12,"subGroup":null,"subGroupOid":0,"subgroup_facultyoid":0,"tableofLessonsName":"Общий распорядок пар","tableofLessonsOid":1,"url1":"","url1_description":"","url2":"","url2_description":""},{"auditorium":"6-436","auditoriumAmount":58,"auditoriumOid":222,"author":"sveta","beginLesson":"15:10","building":"УЛК-6","buildingGid":14,"buildingOid":14,"contentOfLoadOid":9710,"contentOfLoadUID":null,"contentTableOfLessonsName":"5","contentTableOfLessonsOid":5,"createddate":"2022-06-24T11:43:17Z00:00","date":"2022.09.20","dateOfNest":"\/Date(1663610400000+0600)\/","dayOfWeek":2,"dayOfWeekString":"Tue","detailInfo":"","discipline":"Компрессорно-расширительное и насосное оборудование низкотемпературных установок","disciplineOid":6958,"disciplineinplan":null,"disciplinetypeload":0,"duration":2,"endLesson":"16:40","group":null,"groupOid":0,"groupUID":null,"group_facultyoid":0,"hideincapacity":0,"isBan":false,"kindOfWork":"Лекция","kindOfWorkComplexity":0,"kindOfWorkOid":2,"kindOfWorkUid":null,"lecturer":"проф., д.н. КАРАГУСОВ В.И.","lecturerCustomUID":null,"lecturerEmail":"","lecturerOid":157,"lecturerUID":null,"lecturer_rank":"проф., д.н.","lecturer_title":"КАРАГУСОВ В.И.","lessonNumberEnd":5,"lessonNumberStart":5,"lessonOid":66239,"listOfLecturers":[{"lecturer":"проф., д.н. КАРАГУСОВ В.И.","lecturerCustomUID":null,"lecturerEmail":"","lecturerOid":157,"lecturerUID":null,"lecturer_rank":"проф., д.н.","lecturer_title":"КАРАГУСОВ В.И."}],"modifieddate":"2022-06-24T11:54:56Z00:00","note":null,"note_description":"","parentschedule":"1 СЕМ.  НХИ-20  + БИО-201    СВЕТА","replaces":null,"stream":"Поток(Х-201)","streamOid":865,"stream_facultyoid":12,"subGroup":null,"subGroupOid":0,"subgroup_facultyoid":0,"tableofLessonsName":"Общий распорядок пар","tableofLessonsOid":1,"url1":"","url1_description":"","url2":"","url2_description":""},{"auditorium":"8-408","auditoriumAmount":60,"auditoriumOid":141,"author":"sveta","beginLesson":"16:50","building":"УЛК-8","buildingGid":16,"buildingOid":16,"contentOfLoadOid":7923,"contentOfLoadUID":null,"contentTableOfLessonsName":"6","contentTableOfLessonsOid":6,"createddate":"2022-06-24T10:11:47Z00:00","date":"2022.09.20","dateOfNest":"\/Date(1663610400000+0600)\/","dayOfWeek":2,"dayOfWeekString":"Tue","detailInfo":"","discipline":"Прикладная механика","disciplineOid":6031,"disciplineinplan":null,"disciplinetypeload":0,"duration":2,"endLesson":"18:20","group":null,"groupOid":0,"groupUID":null,"group_facultyoid":0,"hideincapacity":0,"isBan":false,"kindOfWork":"Лекция","kindOfWorkComplexity":0,"kindOfWorkOid":2,"kindOfWorkUid":null,"lecturer":"доц., к.н. ЗАХАРЕНКОВ Н.В.","lecturerCustomUID":null,"lecturerEmail":"","lecturerOid":640,"lecturerUID":null,"lecturer_rank":"доц., к.н.","lecturer_title":"ЗАХАРЕНКОВ Н.В.","lessonNumberEnd":6,"lessonNumberStart":6,"lessonOid":65079,"listOfLecturers":[{"lecturer":"доц., к.н. ЗАХАРЕНКОВ Н.В.","lecturerCustomUID":null,"lecturerEmail":"","lecturerOid":640,"lecturerUID":null,"lecturer_rank":"доц., к.н.","lecturer_title":"ЗАХАРЕНКОВ Н.В."}],"modifieddate":"2022-06-24T10:11:47Z00:00","note":null,"note_description":"","parentschedule":"1 СЕМ.  НХИ-20  + БИО-201    СВЕТА","replaces":null,"stream":"Поток(ТМО-201, ТМО-202, ТМО-203, Х-201)","streamOid":795,"stream_facultyoid":12,"subGroup":null,"subGroupOid":0,"subgroup_facultyoid":0,"tableofLessonsName":"Общий распорядок пар","tableofLessonsOid":1,"url1":"","url1_description":"","url2":"","url2_description":""}]