[{"auditorium":"8-606","auditoriumAmount":22,"auditoriumOid":114,"author":"kristina","beginLesson":"08:00","building":"УЛК-8","buildingGid":16,"buildingOid":16,"contentOfLoadOid":13302,"contentOfLoadUID":null,"contentTableOfLessonsName":"1","contentTableOfLessonsOid":1,"createddate":"2022-06-28T13:20:37Z00:00","date":"2022.09.16","dateOfNest":"\/Date(1663264800000+0600)\/","dayOfWeek":5,"dayOfWeekString":"Fri","detailInfo":"","discipline":"Электронные средства сбора и обработки информации","disciplineOid":5424,"disciplineinplan":null,"disciplinetypeload":0,"duration":2,"endLesson":"09:30","group":null,"groupOid":0,"groupUID":null,"group_facultyoid":0,"hideincapacity":0,"isBan":false,"kindOfWork":"Лабораторные работы","kindOfWorkComplexity":0,"kindOfWorkOid":3,"kindOfWorkUid":null,"lecturer":"доц., к.н. ВАЛЬКЕ А.А.","lecturerCustomUID":null,"lecturerEmail":"","lecturerOid":97,"lecturerUID":null,"lecturer_rank":"доц., к.н.","lecturer_title":"ВАЛЬКЕ А.А.","lessonNumberEnd":1,"lessonNumberStart":1,"lessonOid":74231,"listOfLecturers":[{"lecturer":"доц., к.н. ВАЛЬКЕ А.А.","lecturerCustomUID":null,"lecturerEmail":"","lecturerOid":97,"lecturerUID":null,"lecturer_rank":"доц., к.н.","lecturer_title":"ВАЛЬКЕ А.А."}],"modifieddate":"2022-06-28T13:26:47Z00:00","note":null,"note_description":"","parentschedule":"РТФ-19, 1 СЕМЕСТР, ПОСТНИКОВА","replaces":null,"stream":null,"streamOid":0,"stream_facultyoid":0,"subGroup":"ЭН-191\/1","subGroupOid":2410,"subgroup_facultyoid":5,"tableofLessonsName":"Общий распорядок пар","tableofLessonsOid":1,"url1":"","url1_description":"","url2":"","url2_description":""},{"auditorium":"8-602","auditoriumAmount":12,"auditoriumOid":117,"author":"kristina","beginLesson":"09:40","building":"УЛК-8","buildingGid":16,"buildingOid":16,"contentOfLoadOid":13296,"contentOfLoadUID":null,"contentTableOfLessonsName":"2","contentTableOfLessonsOid":2,"createddate":"2022-06-28T13:16:01Z00:00","date":"2022.09.16","dateOfNest":"\/Date(1663264800000+0600)\/","dayOfWeek":5,"dayOfWeekString":"Fri","detailInfo":"","discipline":"Магнитные элементы электронных устройств","disciplineOid":636,"disciplineinplan":null,"disciplinetypeload":0,"duration":2,"endLesson":"11:10","group":null,"groupOid":0,"groupUID":null,"group_facultyoid":0,"hideincapacity":0,"isBan":false,"kindOfWork":"Лабораторные работы","kindOfWorkComplexity":0,"kindOfWorkOid":3,"kindOfWorkUid":null,"lecturer":"доц., к.н. ШКАЕВ А.Г.","lecturerCustomUID":null,"lecturerEmail":"","lecturerOid":394,"lecturerUID":null,"lecturer_rank":"доц., к.н.","lecturer_title":"ШКАЕВ А.Г.","lessonNumberEnd":2,"lessonNumberStart":2,"lessonOid":74224,"listOfLecturers":[{"lecturer":"доц., к.н. ШКАЕВ А.Г.","lecturerCustomUID":null,"lecturerEmail":"","lecturerOid":394,"lecturerUID":null,"lecturer_rank":"доц., к.н.","lecturer_title":"ШКАЕВ А.Г."}],"modifieddate":"2022-06-28T13:26:47Z00:00","note":null,"note_description":"","parentschedule":"РТФ-19, 1 СЕМЕСТР, ПОСТНИКОВА","replaces":null,"stream":null,"streamOid":0,"stream_facultyoid":0,"subGroup":"ЭН-191\/1","subGroupOid":2410,"subgroup_facultyoid":5,"tableofLessonsName":"Общий распорядок пар","tableofLessonsOid":1,"url1":"","url1_description":"","url2":"","url2_description":""},{"auditorium":"8-407","auditoriumAmount":28,"auditoriumOid":142,"author":"kristina","beginLesson":"11:35","building":"УЛК-8","buildingGid":16,"buildingOid":16,"contentOfLoadOid":12466,"contentOfLoadUID":null,"contentTableOfLessonsName":"3","contentTableOfLessonsOid":3,"createddate":"2022-06-28T12:21:25Z00:00","date":"2022.09.16","dateOfNest":"\/Date(1663264800000+0600)\/","dayOfWeek":5,"dayOfWeekString":"Fri","detailInfo":"","discipline":"Устройства сверхвысокой частоты и антенны","disciplineOid":817,"disciplineinplan":null,"disciplinetypeload":0,"duration":2,"endLesson":"13:05","group":null,"groupOid":0,"groupUID":null,"group_facultyoid":0,"hideincapacity":0,"isBan":false,"kindOfWork":"Лабораторные работы","kindOfWorkComplexity":0,"kindOfWorkOid":3,"kindOfWorkUid":null,"lecturer":"проф., д.н. БОГАЧКОВ И.В.","lecturerCustomUID":null,"lecturerEmail":"","lecturerOid":417,"lecturerUID":null,"lecturer_rank":"проф., д.н.","lecturer_title":"БОГАЧКОВ И.В.","lessonNumberEnd":3,"lessonNumberStart":3,"lessonOid":74145,"listOfLecturers":[{"lecturer":"проф., д.н. БОГАЧКОВ И.В.","lecturerCustomUID":null,"lecturerEmail":"","lecturerOid":417,"lecturerUID":null,"lecturer_rank":"проф., д.н.","lecturer_title":"БОГАЧКОВ И.В."}],"modifieddate":"2022-06-28T13:26:47Z00:00","note":null,"note_description":"","parentschedule":"РТФ-19, 1 СЕМЕСТР, ПОСТНИКОВА","replaces":null,"stream":null,"streamOid":0,"stream_facultyoid":0,"subGroup":"ЭН-191\/1","subGroupOid":2410,"subgroup_facultyoid":5,"tableofLessonsName":"Общий распорядок пар","tableofLessonsOid":1,"url1":"","url1_description":"","url2":"","url2_description":""}]