[{"auditorium":"Г-421","auditoriumAmount":20,"auditoriumOid":24,"author":"sveta","beginLesson":"08:00","building":"Главный корпус","buildingGid":3,"buildingOid":3,"contentOfLoadOid":1611,"contentOfLoadUID":null,"contentTableOfLessonsName":"1","contentTableOfLessonsOid":1,"createddate":"2022-09-16T12:20:58Z00:00","date":"2022.09.21","dateOfNest":"\/Date(1663696800000+0600)\/","dayOfWeek":3,"dayOfWeekString":"Wed","detailInfo":"","discipline":"Физическая и коллоидная химия","disciplineOid":6767,"disciplineinplan":null,"disciplinetypeload":0,"duration":2,"endLesson":"09:30","group":"ЗХТ-212","groupOid":334,"groupUID":null,"group_facultyoid":18,"hideincapacity":0,"isBan":false,"kindOfWork":"Экзамен","kindOfWorkComplexity":0,"kindOfWorkOid":5,"kindOfWorkUid":null,"lecturer":"доц., к.н. ТЮМЕНЦЕВА Е.Ю.","lecturerCustomUID":null,"lecturerEmail":"","lecturerOid":843,"lecturerUID":null,"lecturer_rank":"доц., к.н.","lecturer_title":"ТЮМЕНЦЕВА Е.Ю.","lessonNumberEnd":1,"lessonNumberStart":1,"lessonOid":148208,"listOfLecturers":[{"lecturer":"доц., к.н. ТЮМЕНЦЕВА Е.Ю.","lecturerCustomUID":null,"lecturerEmail":"","lecturerOid":843,"lecturerUID":null,"lecturer_rank":"доц., к.н.","lecturer_title":"ТЮМЕНЦЕВА Е.Ю."}],"modifieddate":"2022-09-16T12:21:09Z00:00","note":null,"note_description":"","parentschedule":"ЭКЗ. + 2 СЕМ. ЗХТ-211,212,213, ЗХТ-181,182,183   СВЕТА","replaces":null,"stream":null,"streamOid":0,"stream_facultyoid":0,"subGroup":null,"subGroupOid":0,"subgroup_facultyoid":0,"tableofLessonsName":"Общий распорядок пар","tableofLessonsOid":1,"url1":"","url1_description":"","url2":"","url2_description":""},{"auditorium":"Г-421","auditoriumAmount":20,"auditoriumOid":24,"author":"sveta","beginLesson":"09:40","building":"Главный корпус","buildingGid":3,"buildingOid":3,"contentOfLoadOid":1611,"contentOfLoadUID":null,"contentTableOfLessonsName":"2","contentTableOfLessonsOid":2,"createddate":"2022-09-16T12:20:58Z00:00","date":"2022.09.21","dateOfNest":"\/Date(1663696800000+0600)\/","dayOfWeek":3,"dayOfWeekString":"Wed","detailInfo":"","discipline":"Физическая и коллоидная химия","disciplineOid":6767,"disciplineinplan":null,"disciplinetypeload":0,"duration":2,"endLesson":"11:10","group":"ЗХТ-212","groupOid":334,"groupUID":null,"group_facultyoid":18,"hideincapacity":0,"isBan":false,"kindOfWork":"Экзамен","kindOfWorkComplexity":0,"kindOfWorkOid":5,"kindOfWorkUid":null,"lecturer":"доц., к.н. ТЮМЕНЦЕВА Е.Ю.","lecturerCustomUID":null,"lecturerEmail":"","lecturerOid":843,"lecturerUID":null,"lecturer_rank":"доц., к.н.","lecturer_title":"ТЮМЕНЦЕВА Е.Ю.","lessonNumberEnd":2,"lessonNumberStart":2,"lessonOid":148209,"listOfLecturers":[{"lecturer":"доц., к.н. ТЮМЕНЦЕВА Е.Ю.","lecturerCustomUID":null,"lecturerEmail":"","lecturerOid":843,"lecturerUID":null,"lecturer_rank":"доц., к.н.","lecturer_title":"ТЮМЕНЦЕВА Е.Ю."}],"modifieddate":"2022-09-16T12:21:10Z00:00","note":null,"note_description":"","parentschedule":"ЭКЗ. + 2 СЕМ. ЗХТ-211,212,213, ЗХТ-181,182,183   СВЕТА","replaces":null,"stream":null,"streamOid":0,"stream_facultyoid":0,"subGroup":null,"subGroupOid":0,"subgroup_facultyoid":0,"tableofLessonsName":"Общий распорядок пар","tableofLessonsOid":1,"url1":"","url1_description":"","url2":"","url2_description":""}]