[{"auditorium":"8-421","auditoriumAmount":26,"auditoriumOid":133,"author":"kristina","beginLesson":"09:40","building":"УЛК-8","buildingGid":16,"buildingOid":16,"contentOfLoadOid":7572,"contentOfLoadUID":null,"contentTableOfLessonsName":"2","contentTableOfLessonsOid":2,"createddate":"2022-06-30T12:09:15Z00:00","date":"2022.10.11","dateOfNest":"\/Date(1665424800000+0600)\/","dayOfWeek":2,"dayOfWeekString":"Tue","detailInfo":"","discipline":"Аудит и анализ рисков информационной безопасности","disciplineOid":6570,"disciplineinplan":null,"disciplinetypeload":0,"duration":2,"endLesson":"11:10","group":null,"groupOid":0,"groupUID":null,"group_facultyoid":0,"hideincapacity":0,"isBan":false,"kindOfWork":"Лекция","kindOfWorkComplexity":0,"kindOfWorkOid":2,"kindOfWorkUid":null,"lecturer":"ст.пр. БОЛДЫРЕВА М.Н.","lecturerCustomUID":null,"lecturerEmail":"","lecturerOid":1401,"lecturerUID":null,"lecturer_rank":"ст.пр.","lecturer_title":"БОЛДЫРЕВА М.Н.","lessonNumberEnd":2,"lessonNumberStart":2,"lessonOid":79395,"listOfLecturers":[{"lecturer":"ст.пр. БОЛДЫРЕВА М.Н.","lecturerCustomUID":null,"lecturerEmail":"","lecturerOid":1401,"lecturerUID":null,"lecturer_rank":"ст.пр.","lecturer_title":"БОЛДЫРЕВА М.Н."}],"modifieddate":"2022-06-30T12:09:16Z00:00","note":null,"note_description":"","parentschedule":"РТФ-19, 1 СЕМЕСТР, ПОСТНИКОВА","replaces":null,"stream":"Поток(КЗИ-191)","streamOid":535,"stream_facultyoid":5,"subGroup":null,"subGroupOid":0,"subgroup_facultyoid":0,"tableofLessonsName":"Общий распорядок пар","tableofLessonsOid":1,"url1":"","url1_description":"","url2":"","url2_description":""},{"auditorium":"8-421","auditoriumAmount":26,"auditoriumOid":133,"author":"kristina","beginLesson":"11:35","building":"УЛК-8","buildingGid":16,"buildingOid":16,"contentOfLoadOid":7568,"contentOfLoadUID":null,"contentTableOfLessonsName":"3","contentTableOfLessonsOid":3,"createddate":"2022-06-30T12:09:15Z00:00","date":"2022.10.11","dateOfNest":"\/Date(1665424800000+0600)\/","dayOfWeek":2,"dayOfWeekString":"Tue","detailInfo":"","discipline":"Комплексная система защиты информации на предприятии","disciplineOid":6533,"disciplineinplan":null,"disciplinetypeload":0,"duration":2,"endLesson":"13:05","group":null,"groupOid":0,"groupUID":null,"group_facultyoid":0,"hideincapacity":0,"isBan":false,"kindOfWork":"Лекция","kindOfWorkComplexity":0,"kindOfWorkOid":2,"kindOfWorkUid":null,"lecturer":"доц., к.н. МИХЕЕВ В.В.","lecturerCustomUID":null,"lecturerEmail":"","lecturerOid":495,"lecturerUID":null,"lecturer_rank":"доц., к.н.","lecturer_title":"МИХЕЕВ В.В.","lessonNumberEnd":3,"lessonNumberStart":3,"lessonOid":79402,"listOfLecturers":[{"lecturer":"доц., к.н. МИХЕЕВ В.В.","lecturerCustomUID":null,"lecturerEmail":"","lecturerOid":495,"lecturerUID":null,"lecturer_rank":"доц., к.н.","lecturer_title":"МИХЕЕВ В.В."}],"modifieddate":"2022-06-30T12:09:16Z00:00","note":null,"note_description":"","parentschedule":"РТФ-19, 1 СЕМЕСТР, ПОСТНИКОВА","replaces":null,"stream":"Поток(КЗИ-191)","streamOid":535,"stream_facultyoid":5,"subGroup":null,"subGroupOid":0,"subgroup_facultyoid":0,"tableofLessonsName":"Общий распорядок пар","tableofLessonsOid":1,"url1":"","url1_description":"","url2":"","url2_description":""},{"auditorium":"8-401","auditoriumAmount":22,"auditoriumOid":144,"author":"kristina","beginLesson":"13:15","building":"УЛК-8","buildingGid":16,"buildingOid":16,"contentOfLoadOid":7570,"contentOfLoadUID":null,"contentTableOfLessonsName":"4","contentTableOfLessonsOid":4,"createddate":"2022-06-30T12:09:15Z00:00","date":"2022.10.11","dateOfNest":"\/Date(1665424800000+0600)\/","dayOfWeek":2,"dayOfWeekString":"Tue","detailInfo":"","discipline":"Комплексная система защиты информации на предприятии","disciplineOid":6533,"disciplineinplan":null,"disciplinetypeload":0,"duration":2,"endLesson":"14:45","group":"КЗИ-191","groupOid":441,"groupUID":null,"group_facultyoid":5,"hideincapacity":0,"isBan":false,"kindOfWork":"Практические занятия","kindOfWorkComplexity":0,"kindOfWorkOid":4,"kindOfWorkUid":null,"lecturer":"доц., к.н. МИХЕЕВ В.В.","lecturerCustomUID":null,"lecturerEmail":"","lecturerOid":495,"lecturerUID":null,"lecturer_rank":"доц., к.н.","lecturer_title":"МИХЕЕВ В.В.","lessonNumberEnd":4,"lessonNumberStart":4,"lessonOid":79409,"listOfLecturers":[{"lecturer":"доц., к.н. МИХЕЕВ В.В.","lecturerCustomUID":null,"lecturerEmail":"","lecturerOid":495,"lecturerUID":null,"lecturer_rank":"доц., к.н.","lecturer_title":"МИХЕЕВ В.В."}],"modifieddate":"2022-06-30T12:09:16Z00:00","note":null,"note_description":"","parentschedule":"РТФ-19, 1 СЕМЕСТР, ПОСТНИКОВА","replaces":null,"stream":null,"streamOid":0,"stream_facultyoid":0,"subGroup":null,"subGroupOid":0,"subgroup_facultyoid":0,"tableofLessonsName":"Общий распорядок пар","tableofLessonsOid":1,"url1":"","url1_description":"","url2":"","url2_description":""},{"auditorium":"8-101","auditoriumAmount":24,"auditoriumOid":189,"author":"kristina","beginLesson":"15:10","building":"УЛК-8","buildingGid":16,"buildingOid":16,"contentOfLoadOid":11482,"contentOfLoadUID":null,"contentTableOfLessonsName":"5","contentTableOfLessonsOid":5,"createddate":"2022-09-02T17:28:51Z00:00","date":"2022.10.11","dateOfNest":"\/Date(1665424800000+0600)\/","dayOfWeek":2,"dayOfWeekString":"Tue","detailInfo":"","discipline":"Безопасность вычислительных сетей","disciplineOid":1113,"disciplineinplan":null,"disciplinetypeload":0,"duration":2,"endLesson":"16:40","group":null,"groupOid":0,"groupUID":null,"group_facultyoid":0,"hideincapacity":0,"isBan":false,"kindOfWork":"Лабораторные работы","kindOfWorkComplexity":0,"kindOfWorkOid":3,"kindOfWorkUid":null,"lecturer":"доц., к.н. ЩЕРБА Е.В.","lecturerCustomUID":null,"lecturerEmail":"","lecturerOid":494,"lecturerUID":null,"lecturer_rank":"доц., к.н.","lecturer_title":"ЩЕРБА Е.В.","lessonNumberEnd":5,"lessonNumberStart":5,"lessonOid":137642,"listOfLecturers":[{"lecturer":"доц., к.н. ЩЕРБА Е.В.","lecturerCustomUID":null,"lecturerEmail":"","lecturerOid":494,"lecturerUID":null,"lecturer_rank":"доц., к.н.","lecturer_title":"ЩЕРБА Е.В."}],"modifieddate":"2022-09-02T17:28:52Z00:00","note":null,"note_description":"","parentschedule":"РТФ-19, 1 СЕМЕСТР, ПОСТНИКОВА","replaces":null,"stream":null,"streamOid":0,"stream_facultyoid":0,"subGroup":"КЗИ-191\/2","subGroupOid":1325,"subgroup_facultyoid":5,"tableofLessonsName":"Общий распорядок пар","tableofLessonsOid":1,"url1":"","url1_description":"","url2":"","url2_description":""}]