[{"auditorium":"6-211","auditoriumAmount":90,"auditoriumOid":282,"author":"tanya","beginLesson":"08:00","building":"УЛК-6","buildingGid":14,"buildingOid":14,"contentOfLoadOid":8836,"contentOfLoadUID":null,"contentTableOfLessonsName":"1","contentTableOfLessonsOid":1,"createddate":"2022-06-17T15:39:45Z00:00","date":"2022.10.14","dateOfNest":"\/Date(1665684000000+0600)\/","dayOfWeek":5,"dayOfWeekString":"Fri","detailInfo":"","discipline":"Эксплуатационные режимы работы теплоэнергетического оборудования","disciplineOid":2283,"disciplineinplan":null,"disciplinetypeload":0,"duration":2,"endLesson":"09:30","group":null,"groupOid":0,"groupUID":null,"group_facultyoid":0,"hideincapacity":0,"isBan":false,"kindOfWork":"Лекция","kindOfWorkComplexity":0,"kindOfWorkOid":2,"kindOfWorkUid":null,"lecturer":"ст.пр. ТАРАН М.А.","lecturerCustomUID":null,"lecturerEmail":"","lecturerOid":15,"lecturerUID":null,"lecturer_rank":"ст.пр.","lecturer_title":"ТАРАН М.А.","lessonNumberEnd":1,"lessonNumberStart":1,"lessonOid":55039,"listOfLecturers":[{"lecturer":"ст.пр. ТАРАН М.А.","lecturerCustomUID":null,"lecturerEmail":"","lecturerOid":15,"lecturerUID":null,"lecturer_rank":"ст.пр.","lecturer_title":"ТАРАН М.А."}],"modifieddate":"2022-06-17T15:39:45Z00:00","note":null,"note_description":"","parentschedule":"ТСН, ЭМ, ЭТМ, ПМ-20, 1 СЕМ., ЩЕРБАКОВА","replaces":null,"stream":"Поток(ТЭ-201, ТЭ-202, ЭМ-201)","streamOid":833,"stream_facultyoid":0,"subGroup":null,"subGroupOid":0,"subgroup_facultyoid":0,"tableofLessonsName":"Общий распорядок пар","tableofLessonsOid":1,"url1":"","url1_description":"","url2":"","url2_description":""},{"auditorium":"6-137","auditoriumAmount":24,"auditoriumOid":298,"author":"tanya","beginLesson":"09:40","building":"УЛК-6","buildingGid":14,"buildingOid":14,"contentOfLoadOid":8892,"contentOfLoadUID":null,"contentTableOfLessonsName":"2","contentTableOfLessonsOid":2,"createddate":"2022-06-17T15:41:29Z00:00","date":"2022.10.14","dateOfNest":"\/Date(1665684000000+0600)\/","dayOfWeek":5,"dayOfWeekString":"Fri","detailInfo":"","discipline":"Эксплуатационные режимы работы теплоэнергетического оборудования","disciplineOid":2283,"disciplineinplan":null,"disciplinetypeload":0,"duration":2,"endLesson":"11:10","group":"ЭМ-201","groupOid":798,"groupUID":null,"group_facultyoid":4,"hideincapacity":0,"isBan":false,"kindOfWork":"Практические занятия","kindOfWorkComplexity":0,"kindOfWorkOid":4,"kindOfWorkUid":null,"lecturer":"ст.пр. ТАРАН М.А.","lecturerCustomUID":null,"lecturerEmail":"","lecturerOid":15,"lecturerUID":null,"lecturer_rank":"ст.пр.","lecturer_title":"ТАРАН М.А.","lessonNumberEnd":2,"lessonNumberStart":2,"lessonOid":55070,"listOfLecturers":[{"lecturer":"ст.пр. ТАРАН М.А.","lecturerCustomUID":null,"lecturerEmail":"","lecturerOid":15,"lecturerUID":null,"lecturer_rank":"ст.пр.","lecturer_title":"ТАРАН М.А."}],"modifieddate":"2022-06-17T15:41:29Z00:00","note":null,"note_description":"","parentschedule":"ТСН, ЭМ, ЭТМ, ПМ-20, 1 СЕМ., ЩЕРБАКОВА","replaces":null,"stream":null,"streamOid":0,"stream_facultyoid":0,"subGroup":null,"subGroupOid":0,"subgroup_facultyoid":0,"tableofLessonsName":"Общий распорядок пар","tableofLessonsOid":1,"url1":"","url1_description":"","url2":"","url2_description":""},{"auditorium":"6-303","auditoriumAmount":24,"auditoriumOid":265,"author":"tanya","beginLesson":"11:35","building":"УЛК-6","buildingGid":14,"buildingOid":14,"contentOfLoadOid":6688,"contentOfLoadUID":null,"contentTableOfLessonsName":"3","contentTableOfLessonsOid":3,"createddate":"2022-06-17T16:03:41Z00:00","date":"2022.10.14","dateOfNest":"\/Date(1665684000000+0600)\/","dayOfWeek":5,"dayOfWeekString":"Fri","detailInfo":"","discipline":"Основы тепло- и массообмена","disciplineOid":5976,"disciplineinplan":null,"disciplinetypeload":0,"duration":2,"endLesson":"13:05","group":null,"groupOid":0,"groupUID":null,"group_facultyoid":0,"hideincapacity":0,"isBan":false,"kindOfWork":"Лекция","kindOfWorkComplexity":0,"kindOfWorkOid":2,"kindOfWorkUid":null,"lecturer":"ст.пр. ДОРОФЕЕВ Е.А.","lecturerCustomUID":null,"lecturerEmail":"","lecturerOid":972,"lecturerUID":null,"lecturer_rank":"ст.пр.","lecturer_title":"ДОРОФЕЕВ Е.А.","lessonNumberEnd":3,"lessonNumberStart":3,"lessonOid":55223,"listOfLecturers":[{"lecturer":"ст.пр. ДОРОФЕЕВ Е.А.","lecturerCustomUID":null,"lecturerEmail":"","lecturerOid":972,"lecturerUID":null,"lecturer_rank":"ст.пр.","lecturer_title":"ДОРОФЕЕВ Е.А."}],"modifieddate":"2022-06-17T16:03:42Z00:00","note":null,"note_description":"","parentschedule":"ТСН, ЭМ, ЭТМ, ПМ-20, 1 СЕМ., ЩЕРБАКОВА","replaces":null,"stream":"Поток(ЭМ-201)","streamOid":919,"stream_facultyoid":4,"subGroup":null,"subGroupOid":0,"subgroup_facultyoid":0,"tableofLessonsName":"Общий распорядок пар","tableofLessonsOid":1,"url1":"","url1_description":"","url2":"","url2_description":""},{"auditorium":"6-130","auditoriumAmount":24,"auditoriumOid":302,"author":"tanya","beginLesson":"13:15","building":"УЛК-6","buildingGid":14,"buildingOid":14,"contentOfLoadOid":10980,"contentOfLoadUID":null,"contentTableOfLessonsName":"4","contentTableOfLessonsOid":4,"createddate":"2022-06-17T16:03:57Z00:00","date":"2022.10.14","dateOfNest":"\/Date(1665684000000+0600)\/","dayOfWeek":5,"dayOfWeekString":"Fri","detailInfo":"","discipline":"Основы тепло- и массообмена","disciplineOid":5976,"disciplineinplan":null,"disciplinetypeload":0,"duration":2,"endLesson":"14:45","group":null,"groupOid":0,"groupUID":null,"group_facultyoid":0,"hideincapacity":0,"isBan":false,"kindOfWork":"Лабораторные работы","kindOfWorkComplexity":0,"kindOfWorkOid":3,"kindOfWorkUid":null,"lecturer":"ст.пр. ДОРОФЕЕВ Е.А.","lecturerCustomUID":null,"lecturerEmail":"","lecturerOid":972,"lecturerUID":null,"lecturer_rank":"ст.пр.","lecturer_title":"ДОРОФЕЕВ Е.А.","lessonNumberEnd":4,"lessonNumberStart":4,"lessonOid":55233,"listOfLecturers":[{"lecturer":"ст.пр. ДОРОФЕЕВ Е.А.","lecturerCustomUID":null,"lecturerEmail":"","lecturerOid":972,"lecturerUID":null,"lecturer_rank":"ст.пр.","lecturer_title":"ДОРОФЕЕВ Е.А."}],"modifieddate":"2022-06-17T16:03:57Z00:00","note":null,"note_description":"","parentschedule":"ТСН, ЭМ, ЭТМ, ПМ-20, 1 СЕМ., ЩЕРБАКОВА","replaces":null,"stream":null,"streamOid":0,"stream_facultyoid":0,"subGroup":"ЭМ-201\/2","subGroupOid":2396,"subgroup_facultyoid":4,"tableofLessonsName":"Общий распорядок пар","tableofLessonsOid":1,"url1":"","url1_description":"","url2":"","url2_description":""}]