[{"auditorium":"8-414а","auditoriumAmount":20,"auditoriumOid":137,"author":"kristina","beginLesson":"08:00","building":"УЛК-8","buildingGid":16,"buildingOid":16,"contentOfLoadOid":12485,"contentOfLoadUID":null,"contentTableOfLessonsName":"1","contentTableOfLessonsOid":1,"createddate":"2022-06-29T11:08:23Z00:00","date":"2022.10.10","dateOfNest":"\/Date(1665338400000+0600)\/","dayOfWeek":1,"dayOfWeekString":"Mon","detailInfo":"","discipline":"Электродинамика и распространение радиоволн","disciplineOid":6448,"disciplineinplan":null,"disciplinetypeload":0,"duration":2,"endLesson":"09:30","group":null,"groupOid":0,"groupUID":null,"group_facultyoid":0,"hideincapacity":0,"isBan":false,"kindOfWork":"Лабораторные работы","kindOfWorkComplexity":0,"kindOfWorkOid":3,"kindOfWorkUid":null,"lecturer":"доц., к.н. НИКОНОВ И.В.","lecturerCustomUID":null,"lecturerEmail":"","lecturerOid":415,"lecturerUID":null,"lecturer_rank":"доц., к.н.","lecturer_title":"НИКОНОВ И.В.","lessonNumberEnd":1,"lessonNumberStart":1,"lessonOid":76666,"listOfLecturers":[{"lecturer":"доц., к.н. НИКОНОВ И.В.","lecturerCustomUID":null,"lecturerEmail":"","lecturerOid":415,"lecturerUID":null,"lecturer_rank":"доц., к.н.","lecturer_title":"НИКОНОВ И.В."}],"modifieddate":"2022-06-29T11:08:24Z00:00","note":null,"note_description":"","parentschedule":"РТФ-20, 1 СЕМЕСТР, ПОСТНИКОВА","replaces":null,"stream":null,"streamOid":0,"stream_facultyoid":0,"subGroup":"БИТ-202\/1","subGroupOid":61,"subgroup_facultyoid":5,"tableofLessonsName":"Общий распорядок пар","tableofLessonsOid":1,"url1":"","url1_description":"","url2":"","url2_description":""},{"auditorium":"6-225","auditoriumAmount":38,"auditoriumOid":279,"author":"kristina","beginLesson":"09:40","building":"УЛК-6","buildingGid":14,"buildingOid":14,"contentOfLoadOid":8753,"contentOfLoadUID":null,"contentTableOfLessonsName":"2","contentTableOfLessonsOid":2,"createddate":"2022-06-29T11:08:23Z00:00","date":"2022.10.10","dateOfNest":"\/Date(1665338400000+0600)\/","dayOfWeek":1,"dayOfWeekString":"Mon","detailInfo":"","discipline":"Основы электротехники и радиоэлектроники","disciplineOid":3317,"disciplineinplan":null,"disciplinetypeload":0,"duration":2,"endLesson":"11:10","group":"БИТ-202","groupOid":21,"groupUID":null,"group_facultyoid":5,"hideincapacity":0,"isBan":false,"kindOfWork":"Практические занятия","kindOfWorkComplexity":0,"kindOfWorkOid":4,"kindOfWorkUid":null,"lecturer":"доц., к.н. ВЛАСОВ А.Ю.","lecturerCustomUID":null,"lecturerEmail":"","lecturerOid":412,"lecturerUID":null,"lecturer_rank":"доц., к.н.","lecturer_title":"ВЛАСОВ А.Ю.","lessonNumberEnd":2,"lessonNumberStart":2,"lessonOid":76673,"listOfLecturers":[{"lecturer":"доц., к.н. ВЛАСОВ А.Ю.","lecturerCustomUID":null,"lecturerEmail":"","lecturerOid":412,"lecturerUID":null,"lecturer_rank":"доц., к.н.","lecturer_title":"ВЛАСОВ А.Ю."}],"modifieddate":"2022-06-29T11:08:24Z00:00","note":null,"note_description":"","parentschedule":"РТФ-20, 1 СЕМЕСТР, ПОСТНИКОВА","replaces":null,"stream":null,"streamOid":0,"stream_facultyoid":0,"subGroup":null,"subGroupOid":0,"subgroup_facultyoid":0,"tableofLessonsName":"Общий распорядок пар","tableofLessonsOid":1,"url1":"","url1_description":"","url2":"","url2_description":""},{"auditorium":"8-418","auditoriumAmount":72,"auditoriumOid":134,"author":"kristina","beginLesson":"11:35","building":"УЛК-8","buildingGid":16,"buildingOid":16,"contentOfLoadOid":8636,"contentOfLoadUID":null,"contentTableOfLessonsName":"3","contentTableOfLessonsOid":3,"createddate":"2022-06-29T09:56:34Z00:00","date":"2022.10.10","dateOfNest":"\/Date(1665338400000+0600)\/","dayOfWeek":1,"dayOfWeekString":"Mon","detailInfo":"","discipline":"Общая теория связи","disciplineOid":2820,"disciplineinplan":null,"disciplinetypeload":0,"duration":2,"endLesson":"13:05","group":null,"groupOid":0,"groupUID":null,"group_facultyoid":0,"hideincapacity":0,"isBan":false,"kindOfWork":"Лекция","kindOfWorkComplexity":0,"kindOfWorkOid":2,"kindOfWorkUid":null,"lecturer":"доц., к.н. ЛЕВЧЕНКО В.И.","lecturerCustomUID":null,"lecturerEmail":"","lecturerOid":129,"lecturerUID":null,"lecturer_rank":"доц., к.н.","lecturer_title":"ЛЕВЧЕНКО В.И.","lessonNumberEnd":3,"lessonNumberStart":3,"lessonOid":76379,"listOfLecturers":[{"lecturer":"доц., к.н. ЛЕВЧЕНКО В.И.","lecturerCustomUID":null,"lecturerEmail":"","lecturerOid":129,"lecturerUID":null,"lecturer_rank":"доц., к.н.","lecturer_title":"ЛЕВЧЕНКО В.И."}],"modifieddate":"2022-06-29T09:56:34Z00:00","note":null,"note_description":"","parentschedule":"РТФ-20, 1 СЕМЕСТР, ПОСТНИКОВА","replaces":null,"stream":"Поток(БИТ-201, БИТ-202, КЗИ-201, КЗИ-202)","streamOid":49,"stream_facultyoid":5,"subGroup":null,"subGroupOid":0,"subgroup_facultyoid":0,"tableofLessonsName":"Общий распорядок пар","tableofLessonsOid":1,"url1":"","url1_description":"","url2":"","url2_description":""}]