[{"auditorium":"7-403","auditoriumAmount":26,"auditoriumOid":198,"author":"sveta","beginLesson":"08:00","building":"УЛК-7","buildingGid":15,"buildingOid":15,"contentOfLoadOid":3043,"contentOfLoadUID":null,"contentTableOfLessonsName":"1","contentTableOfLessonsOid":1,"createddate":"2022-08-19T16:27:01Z00:00","date":"2022.10.15","dateOfNest":"\/Date(1665770400000+0600)\/","dayOfWeek":6,"dayOfWeekString":"Sat","detailInfo":"","discipline":"Социология (социальная безопасность)","disciplineOid":4257,"disciplineinplan":null,"disciplinetypeload":0,"duration":2,"endLesson":"09:30","group":null,"groupOid":0,"groupUID":null,"group_facultyoid":0,"hideincapacity":0,"isBan":false,"kindOfWork":"Лекция","kindOfWorkComplexity":0,"kindOfWorkOid":2,"kindOfWorkUid":null,"lecturer":"доц., к.н. РЫБАКОВ Р.В.","lecturerCustomUID":null,"lecturerEmail":"","lecturerOid":449,"lecturerUID":null,"lecturer_rank":"доц., к.н.","lecturer_title":"РЫБАКОВ Р.В.","lessonNumberEnd":1,"lessonNumberStart":1,"lessonOid":108952,"listOfLecturers":[{"lecturer":"доц., к.н. РЫБАКОВ Р.В.","lecturerCustomUID":null,"lecturerEmail":"","lecturerOid":449,"lecturerUID":null,"lecturer_rank":"доц., к.н.","lecturer_title":"РЫБАКОВ Р.В."}],"modifieddate":"2022-08-19T16:27:01Z00:00","note":null,"note_description":"","parentschedule":"1 СЕМ.  НХИ-19 +  БИО-191 + ПБ-181    СВЕТА","replaces":null,"stream":"Поток(ПБ-191)","streamOid":655,"stream_facultyoid":12,"subGroup":null,"subGroupOid":0,"subgroup_facultyoid":0,"tableofLessonsName":"Общий распорядок пар","tableofLessonsOid":1,"url1":"","url1_description":"","url2":"","url2_description":""},{"auditorium":"7-219","auditoriumAmount":24,"auditoriumOid":205,"author":"sveta","beginLesson":"09:40","building":"УЛК-7","buildingGid":15,"buildingOid":15,"contentOfLoadOid":3044,"contentOfLoadUID":null,"contentTableOfLessonsName":"2","contentTableOfLessonsOid":2,"createddate":"2022-08-19T16:27:01Z00:00","date":"2022.10.15","dateOfNest":"\/Date(1665770400000+0600)\/","dayOfWeek":6,"dayOfWeekString":"Sat","detailInfo":"","discipline":"Социология (социальная безопасность)","disciplineOid":4257,"disciplineinplan":null,"disciplinetypeload":0,"duration":2,"endLesson":"11:10","group":"ПБ-191","groupOid":532,"groupUID":null,"group_facultyoid":12,"hideincapacity":0,"isBan":false,"kindOfWork":"Практические занятия","kindOfWorkComplexity":0,"kindOfWorkOid":4,"kindOfWorkUid":null,"lecturer":"доц., к.н. РЫБАКОВ Р.В.","lecturerCustomUID":null,"lecturerEmail":"","lecturerOid":449,"lecturerUID":null,"lecturer_rank":"доц., к.н.","lecturer_title":"РЫБАКОВ Р.В.","lessonNumberEnd":2,"lessonNumberStart":2,"lessonOid":108960,"listOfLecturers":[{"lecturer":"доц., к.н. РЫБАКОВ Р.В.","lecturerCustomUID":null,"lecturerEmail":"","lecturerOid":449,"lecturerUID":null,"lecturer_rank":"доц., к.н.","lecturer_title":"РЫБАКОВ Р.В."}],"modifieddate":"2022-08-19T16:27:01Z00:00","note":null,"note_description":"","parentschedule":"1 СЕМ.  НХИ-19 +  БИО-191 + ПБ-181    СВЕТА","replaces":null,"stream":null,"streamOid":0,"stream_facultyoid":0,"subGroup":null,"subGroupOid":0,"subgroup_facultyoid":0,"tableofLessonsName":"Общий распорядок пар","tableofLessonsOid":1,"url1":"","url1_description":"","url2":"","url2_description":""}]