[{"auditorium":"7-218","auditoriumAmount":16,"auditoriumOid":206,"author":"kristina","beginLesson":"18:30","building":"УЛК-7","buildingGid":15,"buildingOid":15,"contentOfLoadOid":5572,"contentOfLoadUID":null,"contentTableOfLessonsName":"7","contentTableOfLessonsOid":7,"createddate":"2022-08-30T16:09:05Z00:00","date":"2022.10.05","dateOfNest":"\/Date(1664906400000+0600)\/","dayOfWeek":3,"dayOfWeekString":"Wed","detailInfo":"","discipline":"Психодиагностика","disciplineOid":6055,"disciplineinplan":null,"disciplinetypeload":0,"duration":2,"endLesson":"20:00","group":null,"groupOid":0,"groupUID":null,"group_facultyoid":0,"hideincapacity":0,"isBan":false,"kindOfWork":"Лекция","kindOfWorkComplexity":0,"kindOfWorkOid":2,"kindOfWorkUid":null,"lecturer":"ст.пр. ФРЕНКЕЛЬ М.В.","lecturerCustomUID":null,"lecturerEmail":"","lecturerOid":82,"lecturerUID":null,"lecturer_rank":"ст.пр.","lecturer_title":"ФРЕНКЕЛЬ М.В.","lessonNumberEnd":7,"lessonNumberStart":7,"lessonOid":131195,"listOfLecturers":[{"lecturer":"ст.пр. ФРЕНКЕЛЬ М.В.","lecturerCustomUID":null,"lecturerEmail":"","lecturerOid":82,"lecturerUID":null,"lecturer_rank":"ст.пр.","lecturer_title":"ФРЕНКЕЛЬ М.В."}],"modifieddate":"2022-08-30T16:09:06Z00:00","note":null,"note_description":"","parentschedule":"ВПСД-211, 1 СЕМЕСТР, ПОСТНИКОВА","replaces":null,"stream":"Поток(ВПСД-211)","streamOid":115,"stream_facultyoid":7,"subGroup":null,"subGroupOid":0,"subgroup_facultyoid":0,"tableofLessonsName":"Общий распорядок пар","tableofLessonsOid":1,"url1":"","url1_description":"","url2":"","url2_description":""},{"auditorium":"7-218","auditoriumAmount":16,"auditoriumOid":206,"author":"kristina","beginLesson":"20:10","building":"УЛК-7","buildingGid":15,"buildingOid":15,"contentOfLoadOid":5576,"contentOfLoadUID":null,"contentTableOfLessonsName":"8","contentTableOfLessonsOid":8,"createddate":"2022-08-30T16:09:06Z00:00","date":"2022.10.05","dateOfNest":"\/Date(1664906400000+0600)\/","dayOfWeek":3,"dayOfWeekString":"Wed","detailInfo":"","discipline":"Психодиагностика","disciplineOid":6055,"disciplineinplan":null,"disciplinetypeload":0,"duration":2,"endLesson":"21:40","group":"ВПСД-211","groupOid":94,"groupUID":null,"group_facultyoid":7,"hideincapacity":0,"isBan":false,"kindOfWork":"Практические занятия","kindOfWorkComplexity":0,"kindOfWorkOid":4,"kindOfWorkUid":null,"lecturer":"ст.пр. ФРЕНКЕЛЬ М.В.","lecturerCustomUID":null,"lecturerEmail":"","lecturerOid":82,"lecturerUID":null,"lecturer_rank":"ст.пр.","lecturer_title":"ФРЕНКЕЛЬ М.В.","lessonNumberEnd":8,"lessonNumberStart":8,"lessonOid":131203,"listOfLecturers":[{"lecturer":"ст.пр. ФРЕНКЕЛЬ М.В.","lecturerCustomUID":null,"lecturerEmail":"","lecturerOid":82,"lecturerUID":null,"lecturer_rank":"ст.пр.","lecturer_title":"ФРЕНКЕЛЬ М.В."}],"modifieddate":"2022-08-30T16:09:06Z00:00","note":null,"note_description":"","parentschedule":"ВПСД-211, 1 СЕМЕСТР, ПОСТНИКОВА","replaces":null,"stream":null,"streamOid":0,"stream_facultyoid":0,"subGroup":null,"subGroupOid":0,"subgroup_facultyoid":0,"tableofLessonsName":"Общий распорядок пар","tableofLessonsOid":1,"url1":"","url1_description":"","url2":"","url2_description":""}]